payos/__init__.py
payos/constants.py
payos/custom_error.py
payos/index.py
payos/type.py
payos/utils.py
payos_async-1.0.2.dist-info/licenses/LICENSE
payos_async-1.0.2.dist-info/METADATA
payos_async-1.0.2.dist-info/WHEEL
payos_async-1.0.2.dist-info/top_level.txt
payos_async-1.0.2.dist-info/RECORD
