Metadata-Version: 2.4
Name: payos-async
Version: 1.0.2
Summary: Asynchronous client for PayOS API
Author-email: Chisadin chan <tranthanhnam.ccc@gmail.com>
License: MIT
Project-URL: Source, https://github.com/ShindouAris/PayOS-SDK-Async
Project-URL: Bug Tracker, https://github.com/ShindouAris/PayOS-SDK-Async/issues
Requires-Python: >=3.8
License-File: LICENSE
Requires-Dist: aiohttp>=3.8.1
Dynamic: license-file
